histongram-0.2.1.dist-info/METADATA
histongram-0.2.1.dist-info/WHEEL
histongram-0.2.1.dist-info/license_files/LICENSE-APACHE
histongram-0.2.1.dist-info/license_files/LICENSE-MIT
histongram/__init__.py
histongram/__init__.pyi
histongram/py.typed
histongram/histongram.abi3.so
histongram-0.2.1.dist-info/RECORD
