Metadata-Version: 2.1
Name: histongram
Version: 0.2.1
Classifier: Programming Language :: Rust
Classifier: Programming Language :: Python :: Implementation :: CPython
Classifier: Programming Language :: Python :: Implementation :: PyPy
Classifier: License :: OSI Approved :: MIT License
Classifier: License :: OSI Approved :: Apache Software License
License-File: LICENSE-APACHE
License-File: LICENSE-MIT
Summary: Python bindings for histongram
Author: tdittr <td-github@orangecar.org
Author-email: tdittr <td-github@orangecar.org
License: MIT OR Apache-2.0
Requires-Python: >=3.7
Project-URL: Source Code, https://github.com/tdittr/histongram
